xmcdpy/__init__.py
xmcdpy/image_manipulation.py
xmcdpy/image_reading.py
xmcdpy/masking.py
xmcdpy/process_folder_fully.py
xmcdpy/process_xmcd.py
xmcdpy/shifts.py
xmcdpy/stack_display.py
xmcdpy/version.py
XMCDpy-1.2.2.dist-info/LICENSE
XMCDpy-1.2.2.dist-info/METADATA
XMCDpy-1.2.2.dist-info/WHEEL
XMCDpy-1.2.2.dist-info/top_level.txt
XMCDpy-1.2.2.dist-info/RECORD
