Metadata-Version: 2.1
Name: XMCDpy
Version: 1.2.2
Summary: Library for processing XMCD images
Home-page: UNKNOWN
Author: Luka Skoric
License: GNU GENERAL PUBLIC LICENSE
Platform: UNKNOWN
License-File: LICENSE
Requires-Dist: numpy (>=1.20.2)
Requires-Dist: matplotlib (>=3.4.1)
Requires-Dist: scikit-image (>=0.18.1)
Requires-Dist: scipy (>=1.6.2)
Requires-Dist: opencv-python (>=4.4.0.44)
Requires-Dist: PyQt5 (>=5.15.4)
